ZMPY3D_CP/ZMPY3D_CP_CLI_BatchShapeScore.py
ZMPY3D_CP/ZMPY3D_CP_CLI_BatchSuperA2B.py
ZMPY3D_CP/ZMPY3D_CP_CLI_BatchZM.py
ZMPY3D_CP/ZMPY3D_CP_CLI_ShapeScore.py
ZMPY3D_CP/ZMPY3D_CP_CLI_SuperA2B.py
ZMPY3D_CP/ZMPY3D_CP_CLI_ZM.py
ZMPY3D_CP/__all__.py
ZMPY3D_CP/__init__.py
ZMPY3D_CP/cache_data/BinomialCache.pkl
ZMPY3D_CP/cache_data/LogG_CLMCache_MaxOrder06.pkl
ZMPY3D_CP/cache_data/LogG_CLMCache_MaxOrder20.pkl
ZMPY3D_CP/lib/__init__.py
ZMPY3D_CP/lib/calculate_ab_rotation_02.py
ZMPY3D_CP/lib/calculate_ab_rotation_02_all.py
ZMPY3D_CP/lib/calculate_bbox_moment07_cp.py
ZMPY3D_CP/lib/calculate_bbox_moment_2_zm05_cp.py
ZMPY3D_CP/lib/calculate_box_by_grid_width.py
ZMPY3D_CP/lib/calculate_molecular_radius_03_cp.py
ZMPY3D_CP/lib/calculate_zm_by_ab_rotation_01_cp.py
ZMPY3D_CP/lib/eigen_root.py
ZMPY3D_CP/lib/fill_voxel_by_weight_density04.py
ZMPY3D_CP/lib/get_3dzd_121_descriptor02_cp.py
ZMPY3D_CP/lib/get_bbox_moment_xyz_sample_01_cp.py
ZMPY3D_CP/lib/get_ca_distance_info_cp.py
ZMPY3D_CP/lib/get_descriptor_property.py
ZMPY3D_CP/lib/get_global_parameter02.py
ZMPY3D_CP/lib/get_mean_invariant_03_cp.py
ZMPY3D_CP/lib/get_pdb_xyz_ca02.py
ZMPY3D_CP/lib/get_residue_gaussian_density_cache02.py
ZMPY3D_CP/lib/get_residue_radius_map01.py
ZMPY3D_CP/lib/get_residue_weight_map01.py
ZMPY3D_CP/lib/get_total_residue_weight.py
ZMPY3D_CP/lib/get_transform_matrix_from_ab_list_02_cp.py
ZMPY3D_CP/lib/read_file_as_string_list.py
ZMPY3D_CP/lib/set_pdb_xyz_rot_m_01.py
ZMPY3D_CP/lib/write_string_list_as_file.py
ZMPY3D_CP-0.0.2.dist-info/LICENSE
ZMPY3D_CP-0.0.2.dist-info/METADATA
ZMPY3D_CP-0.0.2.dist-info/WHEEL
ZMPY3D_CP-0.0.2.dist-info/entry_points.txt
ZMPY3D_CP-0.0.2.dist-info/top_level.txt
ZMPY3D_CP-0.0.2.dist-info/RECORD
